digi/__init__.py
digi/__main__.py
digi/control.py
digi/data.py
digi/filter.py
digi/handler.py
digi/main.py
digi/mount.py
digi/on.py
digi/pool.py
digi/processor.py
digi/reconcile.py
digi/state.py
digi/util.py
digi/view.py
digi/visual.py
digi/data/__init__.py
digi/data/flow.py
digi/data/pool.py
digi/data/router.py
digi/data/sourcer.py
digi/data/sync.py
digi/data/util.py
digi/data/zed.py
digi/data/zjson.py
digi/dbox/__init__.py
digi/message/__init__.py
digi/message/mqtt.py
digi/tests/__init__.py
digi/tests/test_mount.py
digi/tests/test_processor.py
digi/tests/test_view.py
digi-0.2.9.dist-info/METADATA
digi-0.2.9.dist-info/WHEEL
digi-0.2.9.dist-info/top_level.txt
digi-0.2.9.dist-info/RECORD
