Metadata-Version: 2.1
Name: digi
Version: 0.2.9
Summary: Digi driver library
Home-page: UNKNOWN
Author: Digi Team
Author-email: silveryfu@gmail.com
License: BSD-3-Clause License
Platform: UNKNOWN
Requires-Python: >=3.7
Requires-Dist: pyyaml
Requires-Dist: inflection
Requires-Dist: python-box
Requires-Dist: kubernetes
Requires-Dist: kopf
Requires-Dist: dash
Requires-Dist: pandas
Requires-Dist: pyzed
Requires-Dist: paho-mqtt
